setup.py
blended_google_analytics/__init__.py
blended_google_analytics.egg-info/PKG-INFO
blended_google_analytics.egg-info/SOURCES.txt
blended_google_analytics.egg-info/dependency_links.txt
blended_google_analytics.egg-info/not-zip-safe
blended_google_analytics.egg-info/requires.txt
blended_google_analytics.egg-info/top_level.txt