Metadata-Version: 1.0
Name: blended-google-analytics
Version: 1.0
Summary: Easy google analytics plugin for Blended
Home-page: http://jmroper.com/blended/
Author: John Roper
Author-email: johnroper100@gmail.com
License: GPL3.0
Platform: UNKNOWN
